gwPythonSecTt2/__init__.py
gwPythonSecTt2/module1.py
gwPythonSecTt2-0.1.dist-info/METADATA
gwPythonSecTt2-0.1.dist-info/WHEEL
gwPythonSecTt2-0.1.dist-info/top_level.txt
gwPythonSecTt2-0.1.dist-info/RECORD
